pyqcore/__init__.py
pyqcore/__version__.py
pyqcore/client.py
pyqcore/examples/__init__.py
pyqcore/examples/jpvow.py
pyqcore/examples/data/jpvow_test_x.json
pyqcore/examples/data/jpvow_test_y.json
pyqcore/examples/data/jpvow_train_x.json
pyqcore/examples/data/jpvow_train_y.json
pyqcore-0.2.1.dist-info/LICENSE
pyqcore-0.2.1.dist-info/METADATA
pyqcore-0.2.1.dist-info/WHEEL
pyqcore-0.2.1.dist-info/top_level.txt
pyqcore-0.2.1.dist-info/RECORD
