Metadata-Version: 2.1
Name: pyqcore
Version: 0.2.1
Summary: Library by QuantumCore: Revolutionary ML Company
Home-page: https://github.com/qcore-info/pyqcore
Author: QuantumCore
Author-email: info-dev@qcore.co.jp
License: Apache License 2.0
Platform: UNKNOWN
Classifier: License :: OSI Approved :: Apache Software License
Classifier: Programming Language :: Python
Classifier: Programming Language :: Python :: 3
Classifier: Programming Language :: Python :: 3.5
Classifier: Programming Language :: Python :: 3.6
Classifier: Programming Language :: Python :: 3.7
Classifier: Programming Language :: Python :: Implementation :: PyPy
Requires-Python: >=3.5.0
Requires-Dist: httplib2
Requires-Dist: numpy
Requires-Dist: sklearn
